Metadata-Version: 2.1
Name: hist-plot
Version: 0.5
Summary: Histogram-based visualization approach for visualizing anomaly detection algorithm performance and prediction confidence
Home-page: UNKNOWN
Author: Emmanuel Aboah Boateng
Author-email: emmanuelaboah01@gmail.com
License: MIT
Platform: UNKNOWN
